workload_analyzer/__init__.py
workload_analyzer/cli.py
workload_analyzer/gpu_stats.py
workload_analyzer/monitor.py
workload_analyzer/recommendations.py
workload_analyzer/system_stats.py
workload_analyzer-0.0.7.dist-info/METADATA
workload_analyzer-0.0.7.dist-info/WHEEL
workload_analyzer-0.0.7.dist-info/entry_points.txt
workload_analyzer-0.0.7.dist-info/licenses/LICENSE
workload_analyzer-0.0.7.dist-info/RECORD
