Metadata-Version: 2.4
Name: workload-analyzer
Version: 0.0.7
Summary: Add your description here
Author-email: Nicki Skafte <skaftenicki@gmail.com>
License-File: LICENSE
Classifier: Programming Language :: Python :: 3 :: Only
Classifier: Programming Language :: Python :: 3.12
Classifier: Programming Language :: Python :: 3.13
Requires-Python: >=3.12
Requires-Dist: click<8.2
Requires-Dist: invoke>=2.2
Requires-Dist: loguru>=0.7.3
Requires-Dist: psutil>=7
Requires-Dist: pydantic>=2.11.4
Requires-Dist: pyqt6>=6.9
Requires-Dist: seaborn>=0.13.2
Requires-Dist: typer>=0.15.3
Provides-Extra: cpu
Requires-Dist: torch>=2.6; extra == 'cpu'
Requires-Dist: torchvision>=0.21; extra == 'cpu'
Provides-Extra: cu124
Requires-Dist: torch>=2.6; extra == 'cu124'
Requires-Dist: torchvision>=0.21; extra == 'cu124'
